MANIFEST.in
README.rst
VERSION
setup.cfg
setup.py
bin/sagemakerpyspark-emr-jars
bin/sagemakerpyspark-jars
deps/jars/aws-java-sdk-bundle-1.11.901.jar
deps/jars/aws-java-sdk-core-1.12.262.jar
deps/jars/aws-java-sdk-kms-1.12.262.jar
deps/jars/aws-java-sdk-s3-1.12.262.jar
deps/jars/aws-java-sdk-sagemaker-1.12.262.jar
deps/jars/aws-java-sdk-sagemakerruntime-1.12.262.jar
deps/jars/aws-java-sdk-sts-1.12.262.jar
deps/jars/hadoop-aws-3.3.1.jar
deps/jars/sagemaker-spark_2.12-spark_3.3.0-1.4.5.jar
licenses/LICENSE-hadoop.txt
licenses/LICENSE-htrace.txt
sagemaker_pyspark.egg-info/PKG-INFO
sagemaker_pyspark.egg-info/SOURCES.txt
sagemaker_pyspark.egg-info/dependency_links.txt
sagemaker_pyspark.egg-info/not-zip-safe
sagemaker_pyspark.egg-info/requires.txt
sagemaker_pyspark.egg-info/top_level.txt
src/sagemaker_pyspark/IAMRoleResource.py
src/sagemaker_pyspark/NamePolicy.py
src/sagemaker_pyspark/S3Resources.py
src/sagemaker_pyspark/SageMakerClients.py
src/sagemaker_pyspark/SageMakerEstimator.py
src/sagemaker_pyspark/SageMakerModel.py
src/sagemaker_pyspark/SageMakerResourceCleanup.py
src/sagemaker_pyspark/__init__.py
src/sagemaker_pyspark/wrapper.py
src/sagemaker_pyspark/algorithms/FactorizationMachinesSageMakerEstimator.py
src/sagemaker_pyspark/algorithms/KMeansSageMakerEstimator.py
src/sagemaker_pyspark/algorithms/LDASageMakerEstimator.py
src/sagemaker_pyspark/algorithms/LinearLearnerSageMakerEstimator.py
src/sagemaker_pyspark/algorithms/PCASageMakerEstimator.py
src/sagemaker_pyspark/algorithms/XGBoostSageMakerEstimator.py
src/sagemaker_pyspark/algorithms/__init__.py
src/sagemaker_pyspark/transformation/__init__.py
src/sagemaker_pyspark/transformation/deserializers/__init__.py
src/sagemaker_pyspark/transformation/deserializers/deserializers.py
src/sagemaker_pyspark/transformation/serializers/__init__.py
src/sagemaker_pyspark/transformation/serializers/serializers.py