Metadata-Version: 1.2
Name: sagemaker-pyspark
Version: 1.4.5
Summary: Amazon SageMaker PySpark Bindings
Home-page: https://github.com/aws/sagemaker-spark
Author: Amazon Web Services
License: Apache License 2.0
Platform: UNKNOWN
Requires-Python: >= 3.7
